{
  "table_name": "crons",
  "data": [
    {
      "id": 3,
      "branch_id": 86,
      "interval": "test",
      "created_at": "2021-03-11 23:26:29 UTC",
      "updated_at": "2021-03-11 23:26:29 UTC",
      "next_run": null,
      "last_run": null,
      "dont_run_if_recent_build_exists": false,
      "_dependencies_": {
      }
    },
    {
      "id": 4,
      "branch_id": 86,
      "interval": "test",
      "created_at": "2021-03-11 23:26:29 UTC",
      "updated_at": "2021-03-11 23:26:29 UTC",
      "next_run": null,
      "last_run": null,
      "dont_run_if_recent_build_exists": false,
      "_dependencies_": {
      }
    }
  ]
}